Cookies_Auth/__init__.py
Cookies_Auth/common.py
Cookies_Auth/intro.py
Cookies_Auth/main.py
Cookies_Auth-0.0.4.dist-info/LICENCE.txt
Cookies_Auth-0.0.4.dist-info/METADATA
Cookies_Auth-0.0.4.dist-info/WHEEL
Cookies_Auth-0.0.4.dist-info/top_level.txt
Cookies_Auth-0.0.4.dist-info/RECORD
