Metadata-Version: 2.1
Name: Cookies-Auth
Version: 0.0.4
Summary: Simple authentication system for HWID using pastebin
Home-page: https://www.github.com/Callumgm
Author: Callumgm
Author-email: Callumgm20052005@gmail.com
License: MIT
Keywords: authentication,pastebin,simpleauth
Platform: UNKNOWN
Classifier: Development Status :: 5 - Production/Stable
Classifier: Intended Audience :: Education
Classifier: Operating System :: Microsoft :: Windows :: Windows 10
Classifier: License :: OSI Approved :: MIT License
Classifier: Programming Language :: Python :: 3.8
License-File: LICENCE.txt
Requires-Dist: requests
Requires-Dist: colorama
